sqliteminor/__init__.py
sqliteminor/sqliteminor.py
sqliteminor-1.2.0.dist-info/DESCRIPTION.rst
sqliteminor-1.2.0.dist-info/METADATA
sqliteminor-1.2.0.dist-info/RECORD
sqliteminor-1.2.0.dist-info/WHEEL
sqliteminor-1.2.0.dist-info/entry_points.txt
sqliteminor-1.2.0.dist-info/metadata.json
sqliteminor-1.2.0.dist-info/top_level.txt
