Metadata-Version: 2.0
Name: sqliteminor
Version: 1.2.0
Summary: Python class for working with sqlite databases.
Home-page: https://github.com/aescwork/sqliteminor
Author: aescwork
Author-email: aescwork@protonmail.com
License: MIT
Keywords: sqliteminor setuptools development sqlite database python
Platform: UNKNOWN
Classifier: Development Status :: 5 - Production/Stable
Classifier: Intended Audience :: Developers
Classifier: Topic :: Software Development
Classifier: Topic :: Software Development :: Libraries :: Python Modules
Classifier: Topic :: Database
Classifier: Topic :: Database :: Front-Ends
Classifier: License :: OSI Approved :: MIT License
Classifier: Programming Language :: Python :: 2.7
Classifier: Programming Language :: Python :: 3.5
Requires-Python: >=2.7, ~=3.5
Requires-Dist: sqlite3
